ita_scrapper/__init__.py
ita_scrapper/cli.py
ita_scrapper/config.py
ita_scrapper/example.html
ita_scrapper/exceptions.py
ita_scrapper/models.py
ita_scrapper/parsers.py
ita_scrapper/powertools.js
ita_scrapper/scrapper.py
ita_scrapper/utils.py
ita_scrapper-0.1.3.dist-info/METADATA
ita_scrapper-0.1.3.dist-info/WHEEL
ita_scrapper-0.1.3.dist-info/entry_points.txt
ita_scrapper-0.1.3.dist-info/licenses/LICENSE
ita_scrapper-0.1.3.dist-info/RECORD
