Metadata-Version: 2.4
Name: ita-scrapper
Version: 0.1.3
Summary: A Python library for scraping ITA Matrix travel website using Playwright
Project-URL: Homepage, https://github.com/yourusername/ita-scrapper
Project-URL: Repository, https://github.com/yourusername/ita-scrapper
Project-URL: Issues, https://github.com/yourusername/ita-scrapper/issues
Project-URL: Documentation, https://github.com/yourusername/ita-scrapper#readme
Project-URL: Changelog, https://github.com/yourusername/ita-scrapper/releases
Author: ITA Scrapper Contributors
License: MIT
License-File: LICENSE
Keywords: automation,flight,ita,matrix,playwright,scraping,travel
Classifier: Development Status :: 3 - Alpha
Classifier: Intended Audience :: Developers
Classifier: License :: OSI Approved :: MIT License
Classifier: Programming Language :: Python :: 3
Classifier: Programming Language :: Python :: 3.10
Classifier: Programming Language :: Python :: 3.11
Classifier: Programming Language :: Python :: 3.12
Classifier: Topic :: Internet :: WWW/HTTP :: Browsers
Classifier: Topic :: Internet :: WWW/HTTP :: Dynamic Content
Classifier: Topic :: Software Development :: Libraries :: Python Modules
Classifier: Typing :: Typed
Requires-Python: >=3.10
Requires-Dist: click>=8.0.0
Requires-Dist: playwright>=1.40.0
Requires-Dist: pydantic>=2.0.0
Requires-Dist: python-dateutil>=2.8.0
Requires-Dist: ruff>=0.12.3
Requires-Dist: typing-extensions>=4.0.0
Provides-Extra: dev
Requires-Dist: black>=23.0.0; extra == 'dev'
Requires-Dist: mypy>=1.0.0; extra == 'dev'
Requires-Dist: pre-commit>=3.0.0; extra == 'dev'
Requires-Dist: pytest-asyncio>=0.21.0; extra == 'dev'
Requires-Dist: pytest-cov>=4.0.0; extra == 'dev'
Requires-Dist: pytest-playwright>=0.4.0; extra == 'dev'
Requires-Dist: pytest>=7.0.0; extra == 'dev'
Requires-Dist: ruff>=0.1.0; extra == 'dev'
Provides-Extra: mcp
Requires-Dist: mcp>=1.0.0; extra == 'mcp'
